jmo_security-0.7.1.dist-info/licenses/LICENSE
jmo_security-0.7.1.dist-info/licenses/LICENSE-APACHE
jmo_security-0.7.1.dist-info/licenses/LICENSE-MIT
scripts/__init__.py
scripts/cli/__init__.py
scripts/cli/ci_orchestrator.py
scripts/cli/clone_from_tsv.py
scripts/cli/cpu_utils.py
scripts/cli/jmo.py
scripts/cli/jmotools.py
scripts/cli/path_sanitizers.py
scripts/cli/report_orchestrator.py
scripts/cli/scan_orchestrator.py
scripts/cli/scan_utils.py
scripts/cli/wizard.py
scripts/cli/wizard_generators.py
scripts/cli/scan_jobs/__init__.py
scripts/cli/scan_jobs/gitlab_scanner.py
scripts/cli/scan_jobs/iac_scanner.py
scripts/cli/scan_jobs/image_scanner.py
scripts/cli/scan_jobs/k8s_scanner.py
scripts/cli/scan_jobs/repository_scanner.py
scripts/cli/scan_jobs/url_scanner.py
scripts/core/__init__.py
scripts/core/common_finding.py
scripts/core/compliance_frameworks.py
scripts/core/compliance_mapper.py
scripts/core/config.py
scripts/core/constants.py
scripts/core/email_service.py
scripts/core/exceptions.py
scripts/core/generate_dashboard.py
scripts/core/memory.py
scripts/core/normalize_and_report.py
scripts/core/schema_utils.py
scripts/core/suppress.py
scripts/core/telemetry.py
scripts/core/tool_runner.py
scripts/core/adapters/__init__.py
scripts/core/adapters/aflplusplus_adapter.py
scripts/core/adapters/bandit_adapter.py
scripts/core/adapters/base_adapter.py
scripts/core/adapters/checkov_adapter.py
scripts/core/adapters/falco_adapter.py
scripts/core/adapters/hadolint_adapter.py
scripts/core/adapters/noseyparker_adapter.py
scripts/core/adapters/nuclei_adapter.py
scripts/core/adapters/semgrep_adapter.py
scripts/core/adapters/syft_adapter.py
scripts/core/adapters/trivy_adapter.py
scripts/core/adapters/trufflehog_adapter.py
scripts/core/adapters/zap_adapter.py
scripts/core/reporters/__init__.py
scripts/core/reporters/basic_reporter.py
scripts/core/reporters/compliance_reporter.py
scripts/core/reporters/html_reporter.py
scripts/core/reporters/sarif_reporter.py
scripts/core/reporters/suppression_reporter.py
scripts/core/reporters/yaml_reporter.py
scripts/dev/fix_test_schema_versions.py
scripts/dev/serve_attack_navigator.py
jmo_security-0.7.1.dist-info/METADATA
jmo_security-0.7.1.dist-info/WHEEL
jmo_security-0.7.1.dist-info/entry_points.txt
jmo_security-0.7.1.dist-info/top_level.txt
jmo_security-0.7.1.dist-info/RECORD
