Metadata-Version: 2.4
Name: jmo-security
Version: 0.7.1
Summary: JMo Security Audit Suite (terminal-first, multi-tool, unified outputs, multi-target scanning)
Author-email: James Moceri <general@jmogaming.com>
License: MIT OR Apache-2.0
Project-URL: Homepage, https://jmotools.com
Project-URL: Documentation, https://docs.jmotools.com
Project-URL: Repository, https://github.com/jimmy058910/jmo-security-repo
Project-URL: Bug Tracker, https://github.com/jimmy058910/jmo-security-repo/issues
Project-URL: LinkedIn, https://linkedin.com/in/jimmy-moceri
Keywords: security,scanning,SAST,SBOM,secrets-detection,compliance,OWASP,CWE,DevSecOps,cybersecurity
Classifier: Development Status :: 4 - Beta
Classifier: Intended Audience :: Developers
Classifier: Intended Audience :: System Administrators
Classifier: Topic :: Security
Classifier: Topic :: Software Development :: Quality Assurance
Classifier: Programming Language :: Python :: 3
Classifier: Programming Language :: Python :: 3.10
Classifier: Programming Language :: Python :: 3.11
Classifier: Programming Language :: Python :: 3.12
Classifier: License :: OSI Approved :: MIT License
Classifier: License :: OSI Approved :: Apache Software License
Classifier: Operating System :: OS Independent
Classifier: Operating System :: POSIX :: Linux
Classifier: Operating System :: MacOS
Requires-Python: >=3.8
License-File: LICENSE
License-File: LICENSE-MIT
License-File: LICENSE-APACHE
Requires-Dist: PyYAML>=6.0
Provides-Extra: reporting
Requires-Dist: jsonschema>=4.0; extra == "reporting"
Provides-Extra: email
Requires-Dist: resend>=2.0; extra == "email"
Dynamic: license-file
